data/Electric_Vehicle_Population_Data.csv
data/VSRR_Provisional_Drug_Overdose_Death_Counts.csv
data/best-selling-manga.csv
data/iou_zipcodes_2020.csv
manifests/README.md
manifests/agents/chomsky.json
manifests/agents/tawara.json
manifests/doctor/cardiologist.json
manifests/doctor/gastroenterologist.json
manifests/doctor/neurologist.json
manifests/doctor/nurse.json
manifests/doctor/ophthalmologist.json
manifests/doctor/otolaryngologist.json
manifests/doctor/psychiatrist.json
manifests/doctor/reception.json
manifests/kgraph/code.yml
manifests/kgraph/kg0.yml
manifests/kgraph/kg1.yml
manifests/kgraph/kg_json.yml
manifests/kgraph/knowledge.yml
manifests/main/aiagents.json
manifests/main/browser.json
manifests/main/cal.json
manifests/main/code.json
manifests/main/code_llama.json
manifests/main/code_map.json
manifests/main/code_palm.json
manifests/main/code_vicuna.json
manifests/main/codereview.yml
manifests/main/commit.yml
manifests/main/cook.json
manifests/main/currency.json
manifests/main/definitive.json
manifests/main/dispatcher.json
manifests/main/dot.json
manifests/main/drone.json
manifests/main/gitm.json
manifests/main/gitm_code.json
manifests/main/home.json
manifests/main/kayak.json
manifests/main/legacy.json
manifests/main/names.json
manifests/main/news2.json
manifests/main/noteable.json
manifests/main/paper.yml
manifests/main/spacex.json
manifests/main/weather.json
manifests/main/webpilot.json
manifests/main/wolfram.json
manifests/main/worldnews.json
manifests/manifests.json
manifests/roles1/aiticker.json
manifests/roles1/baby.json
manifests/roles1/business.json
manifests/roles1/crush.json
manifests/roles1/doraemon.json
manifests/roles1/drone.json
manifests/roles1/drone3.json
manifests/roles1/einstein.json
manifests/roles1/goku.json
manifests/roles1/home.json
manifests/roles1/hotel.json
manifests/roles1/kame.json
manifests/roles1/kanryo.json
manifests/roles1/lou-oshiba.json
manifests/roles1/mag2.json
manifests/roles1/obachan.json
manifests/roles1/obachan2.json
slashgpt-0.0.9.dist-info/LICENSE
slashgpt-0.0.9.dist-info/METADATA
slashgpt-0.0.9.dist-info/WHEEL
slashgpt-0.0.9.dist-info/entry_points.txt
slashgpt-0.0.9.dist-info/RECORD
