Metadata-Version: 2.1
Name: slashgpt
Version: 0.0.9
Summary: 
Home-page: https://github.com/snakajima/SlashGPT
License: MIT
Author: snakajima
Author-email: satoshi.nakajima@gmail.com
Requires-Python: >=3.9,<3.13
Classifier: License :: OSI Approved :: MIT License
Classifier: Programming Language :: Python :: 3
Classifier: Programming Language :: Python :: 3.9
Classifier: Programming Language :: Python :: 3.10
Classifier: Programming Language :: Python :: 3.11
Requires-Dist: bs4 (>=0.0.1,<0.0.2)
Requires-Dist: openai (>=1.2.0,<2.0.0)
Requires-Dist: pydantic (==1.10)
Requires-Dist: pyobjc (>=9.2,<10.0) ; sys_platform == "darwin"
Requires-Dist: python-dotenv (==1.0.0)
Requires-Dist: pyyaml (>=6.0.1,<7.0.0)
Requires-Dist: requests-toolbelt (>=1.0.0,<2.0.0)
Requires-Dist: termcolor (>=2.3.0,<3.0.0)
Requires-Dist: tiktoken (>=0.4.0,<0.5.0)
Project-URL: Repository, https://github.com/snakajima/SlashGPT
